Oasys-stubs/__init__.py
Oasys-stubs/AdSec/__init__.pyi
Oasys-stubs/AdSec/DesignCode/__init__.pyi
Oasys-stubs/AdSec/IO/Graphics/Section/__init__.pyi
Oasys-stubs/AdSec/IO/Serialization/__init__.pyi
Oasys-stubs/AdSec/IO/Utility/__init__.pyi
Oasys-stubs/AdSec/Materials/__init__.pyi
Oasys-stubs/AdSec/Materials/StressStrainCurves/__init__.pyi
Oasys-stubs/AdSec/Mesh/__init__.pyi
Oasys-stubs/AdSec/Reinforcement/__init__.pyi
Oasys-stubs/AdSec/Reinforcement/Groups/__init__.pyi
Oasys-stubs/AdSec/Reinforcement/Layers/__init__.pyi
Oasys-stubs/AdSec/Reinforcement/Preloads/__init__.pyi
Oasys-stubs/AdSec/StandardMaterials/__init__.pyi
Oasys-stubs/Collections/__init__.pyi
Oasys-stubs/Exceptions/__init__.pyi
Oasys-stubs/Geometry/Paths2D/__init__.pyi
Oasys-stubs/Profiles/__init__.pyi
Oasys-stubs/Profiles/Properties/__init__.pyi
OasysUnits-stubs/__init__.py
OasysUnits-stubs/__init__.pyi
OasysUnits-stubs/CustomCode/Units/__init__.pyi
OasysUnits-stubs/Units/__init__.pyi
OasysUnits-stubs/Wrappers/__init__.pyi
PythonNetHelpers-stubs/__init__.py
PythonNetHelpers-stubs/__init__.pyi
oasys/adsec/AdSecLogic_AdSec_API.dll
oasys/adsec/AdSec_API.dll
oasys/adsec/AdSec_API.runtimeconfig.json
oasys/adsec/AdSec_IO.dll
oasys/adsec/AdSec_SDK_Implementation.dll
oasys/adsec/AdSol_AdSec_API.dll
oasys/adsec/OaData_AdSec_API.dll
oasys/adsec/OaNumeric_AdSec_API.dll
oasys/adsec/OaUtil_AdSec_API.dll
oasys/adsec/OasysUnits.dll
oasys/adsec/PythonNetHelpers.dll
oasys/adsec/__init__.py
oasys/adsec/addata_AdSec_API.dll
oasys/adsec/application.avf
oasys/adsec/clrcompression.dll
oasys/adsec/concrt140.dll
oasys/adsec/libiomp5md.dll
oasys/adsec/mfc140.dll
oasys/adsec/mfc140chs.dll
oasys/adsec/mfc140cht.dll
oasys/adsec/mfc140deu.dll
oasys/adsec/mfc140enu.dll
oasys/adsec/mfc140esn.dll
oasys/adsec/mfc140fra.dll
oasys/adsec/mfc140ita.dll
oasys/adsec/mfc140jpn.dll
oasys/adsec/mfc140kor.dll
oasys/adsec/mfc140rus.dll
oasys/adsec/mfc140u.dll
oasys/adsec/mfcm140.dll
oasys/adsec/mfcm140u.dll
oasys/adsec/msvcp140.dll
oasys.adsec-2.0.4.234.dist-info/LICENCE.pdf
oasys.adsec-2.0.4.234.dist-info/LICENCE.txt
oasys.adsec-2.0.4.234.dist-info/METADATA
oasys.adsec-2.0.4.234.dist-info/WHEEL
oasys.adsec-2.0.4.234.dist-info/top_level.txt
oasys.adsec-2.0.4.234.dist-info/RECORD
