Metadata-Version: 2.1
Name: oasys.adsec
Version: 2.0.4.234
Summary: Structural analysis and design of sections.
Home-page: https://www.oasys-software.com/products/structural/adsec/
Author: Oasys
Author-email: oasys@arup.com
License: Proprietary License
Project-URL: Bug Tracker, https://www.oasys-software.com/contact-us/
Project-URL: Documentation, https://arup-group.github.io/oasys-combined/adsec-api/
Classifier: Programming Language :: Python :: 3
Classifier: License :: Other/Proprietary License
Classifier: Operating System :: Microsoft :: Windows :: Windows 10
Requires-Python: >=3.7
License-File: LICENCE.pdf
License-File: LICENCE.txt
Requires-Dist: certifi (==2022.9.24)
Requires-Dist: cffi (==1.15.1)
Requires-Dist: pycparser (==2.21)
Requires-Dist: pythonnet (==3.0.1)
Requires-Dist: wincertstore (==0.2)
